reggia/__init__.py
reggia/base.py
reggia-0.1.0a0.dist-info/LICENSE
reggia-0.1.0a0.dist-info/METADATA
reggia-0.1.0a0.dist-info/WHEEL
reggia-0.1.0a0.dist-info/top_level.txt
reggia-0.1.0a0.dist-info/RECORD
