Metadata-Version: 2.1
Name: reggia
Version: 0.1.0a0
Summary: A pythonic-style library that makes regular expressions (regex) simple.
Author-email: "Jesse C. Sealand" <jesse.sealand@outlook.com>
License: MIT License
Project-URL: Homepage, https://github.com/jesse-sealand/reggia
Project-URL: Bug Tracker, https://github.com/jesse-sealand/reggia/issues
Keywords: python3,python,regex
Classifier: Programming Language :: Python :: 3
Classifier: License :: OSI Approved :: MIT License
Classifier: Operating System :: OS Independent
Requires-Python: >=3.8
License-File: LICENSE
